deep_tensor/__init__.py
deep_tensor/constants.py
deep_tensor/integration.py
deep_tensor/interpolation.py
deep_tensor/linalg.py
deep_tensor/verification.py
deep_tensor/bridging_densities/__init__.py
deep_tensor/bridging_densities/bridge.py
deep_tensor/bridging_densities/rare_event.py
deep_tensor/bridging_densities/single_layer.py
deep_tensor/bridging_densities/tempering.py
deep_tensor/debiasing/__init__.py
deep_tensor/debiasing/importance_sampling.py
deep_tensor/debiasing/mcmc.py
deep_tensor/debiasing/mcmc_new/__init__.py
deep_tensor/debiasing/mcmc_new/kernel.py
deep_tensor/debiasing/mcmc_new/mcmc.py
deep_tensor/debiasing/mcmc_new/pcn.py
deep_tensor/domains/__init__.py
deep_tensor/domains/algebraic_mapping.py
deep_tensor/domains/bounded_domain.py
deep_tensor/domains/domain.py
deep_tensor/domains/linear_domain.py
deep_tensor/domains/logarithmic_mapping.py
deep_tensor/domains/mapped_domain.py
deep_tensor/ftt/__init__.py
deep_tensor/ftt/approx_bases.py
deep_tensor/ftt/directions.py
deep_tensor/ftt/eftt_options.py
deep_tensor/ftt/ftt.py
deep_tensor/ftt/tt.py
deep_tensor/ftt/tt_options.py
deep_tensor/irt/__init__.py
deep_tensor/irt/dirt.py
deep_tensor/irt/dirt_options.py
deep_tensor/irt/sirt.py
deep_tensor/polynomials/__init__.py
deep_tensor/polynomials/basis_1d.py
deep_tensor/polynomials/cdf_1d.py
deep_tensor/polynomials/cdf_constructor.py
deep_tensor/polynomials/cdf_data.py
deep_tensor/polynomials/piecewise/__init__.py
deep_tensor/polynomials/piecewise/lagrange_1.py
deep_tensor/polynomials/piecewise/lagrange_1_cdf.py
deep_tensor/polynomials/piecewise/lagrange_1_cdf_alt.py
deep_tensor/polynomials/piecewise/lagrange_p.py
deep_tensor/polynomials/piecewise/lagrange_p_cdf.py
deep_tensor/polynomials/piecewise/piecewise.py
deep_tensor/polynomials/piecewise/piecewise_cdf.py
deep_tensor/polynomials/piecewise/piecewise_chebyshev_cdf.py
deep_tensor/polynomials/spectral/__init__.py
deep_tensor/polynomials/spectral/chebyshev_1st.py
deep_tensor_py-1.2.0.dist-info/licenses/COPYING
deep_tensor_py-1.2.0.dist-info/METADATA
deep_tensor_py-1.2.0.dist-info/WHEEL
deep_tensor_py-1.2.0.dist-info/top_level.txt
deep_tensor_py-1.2.0.dist-info/RECORD
