Metadata-Version: 2.4
Name: deep-tensor-py
Version: 1.2.0
Summary: A PyTorch implementation of the deep inverse Rosenblatt transport (DIRT) algorithm.
Author-email: Alex de Beer <adeb0907@uni.sydney.edu.au>
License-Expression: GPL-3.0-or-later
Project-URL: Homepage, https://github.com/DeepTransport/deep-tensor-py
Project-URL: Documentation, https://deeptransport.github.io/deep-tensor-py/
Project-URL: Issues, https://github.com/DeepTransport/deep-tensor-py/issues
Classifier: Programming Language :: Python :: 3
Classifier: Operating System :: OS Independent
Requires-Python: >=3.9
License-File: COPYING
Requires-Dist: h5py
Requires-Dist: torch
Dynamic: license-file
